real_random/__init__.py
real_random/core.py
real_random-0.1.1.dist-info/METADATA
real_random-0.1.1.dist-info/WHEEL
real_random-0.1.1.dist-info/top_level.txt
real_random-0.1.1.dist-info/RECORD
