Metadata-Version: 2.4
Name: real-random
Version: 0.1.1
Summary: Entropy-based random generator using microphone audio to produce real random floats, integers, strings, and choices.
Author-email: Croketillo <croketillo@gmail.com>
License-Expression: MIT
Project-URL: Homepage, https://github.com/croketillo/real-random
Project-URL: Repository, https://github.com/croketillo/real-random
Project-URL: Issues, https://github.com/croketillo/real-random/issues
Keywords: random,entropy,microphone,audio,non-deterministic,real randomness,true random,sound-based randomness
Requires-Python: >=3.7
Requires-Dist: numpy>=1.20
Requires-Dist: sounddevice>=0.4.5
